touchdb/Database.py
touchdb/Exceptions.py
touchdb/__init__.py
touchdb-0.0.5.dist-info/METADATA
touchdb-0.0.5.dist-info/WHEEL
touchdb-0.0.5.dist-info/top_level.txt
touchdb-0.0.5.dist-info/RECORD
