Metadata-Version: 2.1
Name: touchdb
Version: 0.0.5
Summary: Document based light weight NoSQL database.
Author: Kabilan Mahathevan
Author-email: <kabilanen@gmail.com>
Keywords: touchdb,python,embedded database,nosql,document
Classifier: Development Status :: 1 - Planning
Classifier: Intended Audience :: Developers
Classifier: Programming Language :: Python :: 3
Classifier: Operating System :: Unix
Classifier: Operating System :: MacOS :: MacOS X
Classifier: Operating System :: Microsoft :: Windows
